spatiomic/__init__.py
spatiomic/__init__.pyi
spatiomic/py.typed
spatiomic/_internal/__init__.py
spatiomic/_internal/_anndata_method.py
spatiomic/_internal/_check_channel_dimension.py
spatiomic/_internal/_data_method.py
spatiomic/_internal/_get_neighbor_finder.py
spatiomic/_internal/_import_package.py
spatiomic/_internal/_seed_method.py
spatiomic/cluster/__init__.py
spatiomic/cluster/_agglomerative.py
spatiomic/cluster/_base.py
spatiomic/cluster/_kmeans.py
spatiomic/cluster/_leiden.py
spatiomic/data/__init__.py
spatiomic/data/_anndata_from_array.py
spatiomic/data/_array_from_sdata.py
spatiomic/data/_read.py
spatiomic/data/_subsample.py
spatiomic/data/_subset.py
spatiomic/dimension/__init__.py
spatiomic/dimension/_base.py
spatiomic/dimension/_pca.py
spatiomic/dimension/_som.py
spatiomic/dimension/_tsne.py
spatiomic/dimension/_umap.py
spatiomic/neighbor/__init__.py
spatiomic/neighbor/_knn_graph.py
spatiomic/neighbor/_snn_graph.py
spatiomic/plot/__init__.py
spatiomic/plot/_cluster_contributor_histogram.py
spatiomic/plot/_cluster_contributors.py
spatiomic/plot/_cluster_image.py
spatiomic/plot/_cluster_legend.py
spatiomic/plot/_cluster_location.py
spatiomic/plot/_cluster_scatter.py
spatiomic/plot/_cluster_selection.py
spatiomic/plot/_colormap.py
spatiomic/plot/_connectivity_graph.py
spatiomic/plot/_marker_expression.py
spatiomic/plot/_registration_similarity.py
spatiomic/plot/_registration_slope.py
spatiomic/plot/_segmentation_overlay.py
spatiomic/plot/_som_clusters.py
spatiomic/plot/_som_distance.py
spatiomic/plot/_som_marker_expression.py
spatiomic/plot/_spatial_graph.py
spatiomic/plot/_volcano.py
spatiomic/process/__init__.py
spatiomic/process/_arcsinh.py
spatiomic/process/_base.py
spatiomic/process/_clip.py
spatiomic/process/_log1p.py
spatiomic/process/_normalize.py
spatiomic/process/_register.py
spatiomic/process/_zscore.py
spatiomic/segment/__init__.py
spatiomic/segment/_assign_communities.py
spatiomic/segment/_cellpose.py
spatiomic/segment/_count_clusters.py
spatiomic-0.9.2.dist-info/METADATA
spatiomic-0.9.2.dist-info/WHEEL
spatiomic-0.9.2.dist-info/licenses/LICENSE
spatiomic-0.9.2.dist-info/RECORD
