Metadata-Version: 2.4
Name: spatiomic
Version: 0.9.2
Summary: A python toolbox for spatial omics analysis.
Project-URL: Home, https://github.com/complextissue/spatiomic
Project-URL: Source, https://github.com/complextissue/spatiomic
Project-URL: Documentation, https://spatiomic.org
Author-email: Malte Kuehl <malte.kuehl@clin.au.dk>
License:                     GNU GENERAL PUBLIC LICENSE
License-File: LICENSE
Classifier: Development Status :: 4 - Beta
Classifier: Intended Audience :: Healthcare Industry
Classifier: Intended Audience :: Science/Research
Classifier: License :: OSI Approved :: GNU General Public License v3 (GPLv3)
Classifier: Natural Language :: English
Classifier: Operating System :: OS Independent
Classifier: Programming Language :: Python :: 3
Classifier: Programming Language :: Python :: 3.11
Classifier: Programming Language :: Python :: 3.12
Classifier: Programming Language :: Python :: 3.13
Classifier: Typing :: Typed
Requires-Python: >=3.11
Requires-Dist: adjusttext
Requires-Dist: anndata>=0.12.0
Requires-Dist: astroid==3.3.11
Requires-Dist: colorcet
Requires-Dist: esda>=2.7.0
Requires-Dist: joblib
Requires-Dist: lazy-loader
Requires-Dist: llvmlite>=0.39.0
Requires-Dist: matplotlib
Requires-Dist: networkx
Requires-Dist: numpy>=2
Requires-Dist: pandas>=2
Requires-Dist: pysal
Requires-Dist: python-igraph
Requires-Dist: scikit-image
Requires-Dist: scikit-learn
Requires-Dist: scipy-stubs
Requires-Dist: scipy>=0.16.1
Requires-Dist: seaborn
Requires-Dist: statsmodels
Requires-Dist: umap-learn
Requires-Dist: xpysom==1.0.7
Provides-Extra: cellpose
Requires-Dist: cellpose<5,>=4.0.1; extra == 'cellpose'
Provides-Extra: cuda-11
Requires-Dist: cucim-cu11>=24.10.0; extra == 'cuda-11'
Requires-Dist: cugraph-cu11>=24.10.0; extra == 'cuda-11'
Requires-Dist: cuml-cu11>=24.10.0; extra == 'cuda-11'
Requires-Dist: nx-cugraph-cu11>=24.10.0; extra == 'cuda-11'
Provides-Extra: cuda-12
Requires-Dist: cucim-cu12>=24.10.0; extra == 'cuda-12'
Requires-Dist: cugraph-cu12>=24.10.0; extra == 'cuda-12'
Requires-Dist: cuml-cu12>=24.10.0; extra == 'cuda-12'
Requires-Dist: nx-cugraph-cu12>=24.10.0; extra == 'cuda-12'
Provides-Extra: spatialdata
Requires-Dist: spatialdata==0.6.1; extra == 'spatialdata'
